test_pb2.py
test_pb2_grpc.py
donotgiveup-0.1.dist-info/METADATA
donotgiveup-0.1.dist-info/WHEEL
donotgiveup-0.1.dist-info/top_level.txt
donotgiveup-0.1.dist-info/RECORD
